{
  "format_version": 3,
  "format_uuid": "289f771f-2c9a-4d73-9f3f-8492495a924d",
  "tooth": "github.com/Dofes/ContentLogBlocker",
  "version": "0.0.4",
  "info": {
    "name": "ContentLogBlocker",
    "description": "A simple plugin to block the content log you don\u0027t want to see.",
    "tags": [
      "levilamina",
      "plugin",
      "contentlog"
    ],
    "avatar_url": ""
  },
  "variants": [
    {
      "label": "",
      "platform": "",
      "dependencies": {},
      "assets": [
        {
          "type": "zip",
          "urls": [
            "https://github.com/Dofes/ContentLogBlocker/releases/download/v0.0.4/ContentLogBlocker-windows-x64.zip"
          ],
          "placements": [
            {
              "type": "dir",
              "src": "ContentLogBlocker/",
              "dest": "plugins/ContentLogBlocker/"
            }
          ]
        }
      ],
      "preserve_files": [],
      "remove_files": [],
      "scripts": {
        "pre_install": [],
        "post_install": [],
        "pre_uninstall": [],
        "post_uninstall": []
      }
    }
  ]
}